proctitle/__init__.py
ProcTitle-0.1.6.dist-info/LICENSE.txt
ProcTitle-0.1.6.dist-info/METADATA
ProcTitle-0.1.6.dist-info/WHEEL
ProcTitle-0.1.6.dist-info/top_level.txt
ProcTitle-0.1.6.dist-info/RECORD
