Metadata-Version: 2.1
Name: ProcTitle
Version: 0.1.6
Summary: Context Manager to set/reset the current process name.
Home-page: http://pypi.python.org/pypi/ProcTitle/
Author: Glenn Franxman
Author-email: gfranxman@gmail.com
License: ISC License
Platform: UNKNOWN
License-File: LICENSE.txt
